PrintScript/__init__.py
PrintScript/algorithm.py
PrintScript/common.py
PrintScript/device.py
PrintScript/pcx.py
PrintScript/tspl.py
PrintScript/zpl.py
PrintScript-1.3.0.dist-info/LICENSE
PrintScript-1.3.0.dist-info/METADATA
PrintScript-1.3.0.dist-info/WHEEL
PrintScript-1.3.0.dist-info/top_level.txt
PrintScript-1.3.0.dist-info/RECORD
