Metadata-Version: 2.1
Name: PrintScript
Version: 1.3.0
Summary: A package for making print scripts
Author-email: Alex Chen <laplacedoge@gmail.com>
Project-URL: Homepage, https://github.com/laplacedoge/PrintScript
Project-URL: Issues, https://github.com/laplacedoge/PrintScript/issues
Classifier: Programming Language :: Python :: 3
Classifier: License :: OSI Approved :: MIT License
Classifier: Operating System :: OS Independent
Requires-Python: >=3.8
License-File: LICENSE
Requires-Dist: opencv-python
Requires-Dist: crcmod
Requires-Dist: numpy
Requires-Dist: numba
